zaapy/__init__.py
zaapy/__main__.py
zaapy/__version__.py
zaapy/config.py
zaapy/main.py
zaapy/multi_tab.py
zaapy/parser.py
zaapy/api/__init__.py
zaapy/api/analysis.py
zaapy/api/from_simulation.py
zaapy/api/satellite.py
zaapy-0.2.1.dist-info/LICENSE
zaapy-0.2.1.dist-info/METADATA
zaapy-0.2.1.dist-info/WHEEL
zaapy-0.2.1.dist-info/entry_points.txt
zaapy-0.2.1.dist-info/top_level.txt
zaapy-0.2.1.dist-info/RECORD
