Metadata-Version: 2.1
Name: zaapy
Version: 0.2.1
Summary: A tool to analyze results from Zeltron
Author: A. Soudais
License: GPL-3.0
Classifier: License :: OSI Approved :: GNU General Public License v3 (GPLv3)
Classifier: Programming Language :: Python :: 3
Classifier: Programming Language :: Python :: 3 :: Only
Classifier: Typing :: Typed
Requires-Python: >=3.8
License-File: LICENSE
Requires-Dist: matplotlib >=3.5.0
Requires-Dist: numpy >=1.18.5
Requires-Dist: packaging >=21.3
Requires-Dist: scipy >=1.6.1
Requires-Dist: h5py >=3.8.0
